cecli/__init__.py
cecli/__main__.py
cecli/_version.py
cecli/args.py
cecli/args_formatter.py
cecli/change_tracker.py
cecli/deprecated_args.py
cecli/diffs.py
cecli/dump.py
cecli/editor.py
cecli/exceptions.py
cecli/format_settings.py
cecli/help.py
cecli/help_pats.py
cecli/history.py
cecli/io.py
cecli/linter.py
cecli/llm.py
cecli/main.py
cecli/mdstream.py
cecli/models.py
cecli/onboarding.py
cecli/reasoning_tags.py
cecli/repo.py
cecli/repomap.py
cecli/report.py
cecli/run_cmd.py
cecli/scrape.py
cecli/sendchat.py
cecli/sessions.py
cecli/special.py
cecli/urls.py
cecli/utils.py
cecli/versioncheck.py
cecli/voice.py
cecli/waiting.py
cecli/watch.py
cecli/watch_prompts.py
cecli/coders/__init__.py
cecli/coders/agent_coder.py
cecli/coders/architect_coder.py
cecli/coders/ask_coder.py
cecli/coders/base_coder.py
cecli/coders/chat_chunks.py
cecli/coders/context_coder.py
cecli/coders/copypaste_coder.py
cecli/coders/editblock_coder.py
cecli/coders/editblock_fenced_coder.py
cecli/coders/editblock_func_coder.py
cecli/coders/editor_diff_fenced_coder.py
cecli/coders/editor_editblock_coder.py
cecli/coders/editor_whole_coder.py
cecli/coders/help_coder.py
cecli/coders/patch_coder.py
cecli/coders/search_replace.py
cecli/coders/shell.py
cecli/coders/single_wholefile_func_coder.py
cecli/coders/udiff_coder.py
cecli/coders/udiff_simple.py
cecli/coders/wholefile_coder.py
cecli/coders/wholefile_func_coder.py
cecli/commands/__init__.py
cecli/commands/add.py
cecli/commands/agent.py
cecli/commands/architect.py
cecli/commands/ask.py
cecli/commands/chat_mode.py
cecli/commands/clear.py
cecli/commands/code.py
cecli/commands/command_prefix.py
cecli/commands/commit.py
cecli/commands/compact.py
cecli/commands/context.py
cecli/commands/context_blocks.py
cecli/commands/context_management.py
cecli/commands/copy.py
cecli/commands/copy_context.py
cecli/commands/core.py
cecli/commands/diff.py
cecli/commands/drop.py
cecli/commands/editor.py
cecli/commands/editor_model.py
cecli/commands/exit.py
cecli/commands/git.py
cecli_dev-0.96.7.dist-info/licenses/LICENSE.txt
cecli_dev-0.96.7.dist-info/METADATA
cecli_dev-0.96.7.dist-info/WHEEL
cecli_dev-0.96.7.dist-info/entry_points.txt
cecli_dev-0.96.7.dist-info/top_level.txt
cecli_dev-0.96.7.dist-info/RECORD
