Metadata-Version: 2.4
Name: cecli-dev
Version: 0.96.7
Summary: we also can't pronounce cecli
Project-URL: Homepage, https://github.com/dwash96/cecli
Project-URL: Documentation, https://github.com/dwash96/cecli
Project-URL: Repository, https://github.com/dwash96/cecli
Classifier: Development Status :: 4 - Beta
Classifier: Environment :: Console
Classifier: Intended Audience :: Developers
Classifier: License :: OSI Approved :: Apache Software License
Classifier: Programming Language :: Python :: 3
Classifier: Programming Language :: Python :: 3.10
Classifier: Programming Language :: Python :: 3.11
Classifier: Programming Language :: Python :: 3.12
Classifier: Programming Language :: Python
Classifier: Topic :: Software Development
Requires-Python: >=3.10
License-File: LICENSE.txt
Requires-Dist: pydub>=0.25.1
Requires-Dist: configargparse>=1.7.1
Requires-Dist: GitPython>=3.1.45
Requires-Dist: jsonschema>=4.25.0
Requires-Dist: rich>=14.1.0
Requires-Dist: prompt_toolkit
Requires-Dist: backoff>=2.2.1
Requires-Dist: pathspec>=0.12.1
Requires-Dist: diskcache>=5.6.3
Requires-Dist: grep_ast
Requires-Dist: packaging>=25.0
Requires-Dist: sounddevice>=0.5.2
Requires-Dist: soundfile>=0.13.1
Requires-Dist: beautifulsoup4>=4.13.4
Requires-Dist: PyYAML>=6.0.2
Requires-Dist: diff-match-patch>=20241021
Requires-Dist: pypandoc>=1.15
Requires-Dist: litellm>=1.80.11
Requires-Dist: flake8>=7.3.0
Requires-Dist: importlib_resources
Requires-Dist: pyperclip>=1.9.0
Requires-Dist: pexpect>=4.9.0
Requires-Dist: json5>=0.12.0
Requires-Dist: psutil>=7.0.0
Requires-Dist: watchfiles>=1.1.0
Requires-Dist: socksio>=1.0.0
Requires-Dist: pillow>=11.3.0
Requires-Dist: shtab>=1.7.2
Requires-Dist: oslex>=0.1.3
Requires-Dist: mcp>=1.24.0
Requires-Dist: textual>=6.0.0
Requires-Dist: truststore
Requires-Dist: xxhash>=3.6.0
Requires-Dist: rustworkx>=0.15.0
Requires-Dist: scipy>=1.15.3
Requires-Dist: importlib-metadata>=7.2.1
Requires-Dist: tomli>=2.3.0; python_version <= "3.10"
Requires-Dist: tree-sitter==0.23.2; python_version < "3.10"
Requires-Dist: tree-sitter>=0.25.1; python_version >= "3.10"
Provides-Extra: dev
Requires-Dist: pytest; extra == "dev"
Requires-Dist: pytest-asyncio; extra == "dev"
Requires-Dist: pytest-env; extra == "dev"
Requires-Dist: pytest-mock; extra == "dev"
Requires-Dist: pip-tools; extra == "dev"
Requires-Dist: lox; extra == "dev"
Requires-Dist: matplotlib; extra == "dev"
Requires-Dist: pandas; extra == "dev"
Requires-Dist: typer; extra == "dev"
Requires-Dist: imgcat; extra == "dev"
Requires-Dist: pre-commit; extra == "dev"
Requires-Dist: cogapp; extra == "dev"
Requires-Dist: semver; extra == "dev"
Requires-Dist: codespell; extra == "dev"
Requires-Dist: uv; extra == "dev"
Requires-Dist: google-cloud-bigquery; extra == "dev"
Provides-Extra: help
Requires-Dist: llama-index-embeddings-huggingface; extra == "help"
Requires-Dist: numpy>=1.26.4; extra == "help"
Provides-Extra: playwright
Requires-Dist: playwright; extra == "playwright"
Provides-Extra: tui
Dynamic: license-file
